[
  {
    "url": "https://www.zentraleserien-hybridesuche.zh.ch",
    "timestamp": "2026-04-03T17:28:01.726158+00:00",
    "status": "online",
    "responseTime": 552,
    "statusCode": 200,
    "error": null,
    "attemptCount": 1,
    "confirmedFailure": false,
    "message": null,
    "uptime": {
      "uptime": "99.83",
      "totalChecks": 1148,
      "onlineChecks": 1146
    }
  },
  {
    "url": "https://www.zentraleserien.zh.ch/documents/abl/ABl_1966__S__568-589_?norm=on",
    "timestamp": "2026-04-03T17:28:02.279328+00:00",
    "status": "online",
    "responseTime": 2954,
    "statusCode": 200,
    "error": null,
    "attemptCount": 1,
    "confirmedFailure": false,
    "message": null,
    "uptime": {
      "uptime": "97.84",
      "totalChecks": 740,
      "onlineChecks": 724
    }
  }
]