[
  {
    "url": "https://www.zentraleserien-hybridesuche.zh.ch",
    "timestamp": "2026-04-05T18:33:18.395289+00:00",
    "status": "online",
    "responseTime": 941,
    "statusCode": 200,
    "error": null,
    "attemptCount": 1,
    "confirmedFailure": false,
    "message": null,
    "uptime": {
      "uptime": "99.83",
      "totalChecks": 1190,
      "onlineChecks": 1188
    }
  },
  {
    "url": "https://www.zentraleserien.zh.ch/documents/abl/ABl_1966__S__568-589_?norm=on",
    "timestamp": "2026-04-05T18:33:19.337117+00:00",
    "status": "online",
    "responseTime": 2335,
    "statusCode": 200,
    "error": null,
    "attemptCount": 1,
    "confirmedFailure": false,
    "message": null,
    "uptime": {
      "uptime": "97.95",
      "totalChecks": 782,
      "onlineChecks": 766
    }
  }
]