[
  {
    "url": "https://www.zentraleserien-hybridesuche.zh.ch",
    "timestamp": "2026-04-21T01:56:19.596358+00:00",
    "status": "online",
    "responseTime": 909,
    "statusCode": 200,
    "error": null,
    "attemptCount": 1,
    "confirmedFailure": false,
    "message": null,
    "uptime": {
      "uptime": "99.90",
      "totalChecks": 1000,
      "onlineChecks": 999
    }
  },
  {
    "url": "https://www.zentraleserien.zh.ch/documents/abl/ABl_1966__S__568-589_?norm=on",
    "timestamp": "2026-04-21T01:56:20.506461+00:00",
    "status": "online",
    "responseTime": 2073,
    "statusCode": 200,
    "error": null,
    "attemptCount": 1,
    "confirmedFailure": false,
    "message": null,
    "uptime": {
      "uptime": "98.20",
      "totalChecks": 1000,
      "onlineChecks": 982
    }
  }
]