[
  {
    "url": "https://www.zentraleserien-hybridesuche.zh.ch",
    "timestamp": "2026-04-02T18:46:06.886397+00:00",
    "status": "online",
    "responseTime": 1031,
    "statusCode": 200,
    "error": null,
    "attemptCount": 1,
    "confirmedFailure": false,
    "message": null,
    "uptime": {
      "uptime": "99.82",
      "totalChecks": 1129,
      "onlineChecks": 1127
    }
  },
  {
    "url": "https://www.zentraleserien.zh.ch/documents/abl/ABl_1966__S__568-589_?norm=on",
    "timestamp": "2026-04-02T18:46:07.918164+00:00",
    "status": "online",
    "responseTime": 2399,
    "statusCode": 200,
    "error": null,
    "attemptCount": 1,
    "confirmedFailure": false,
    "message": null,
    "uptime": {
      "uptime": "97.78",
      "totalChecks": 721,
      "onlineChecks": 705
    }
  }
]